ltctplugin/ftflasher/__init__.py
ltctplugin/ftflasher/ftflasher.wxui
ltctplugin/ftflasher/ftflasher.xrc
ltctplugin/ftflasher/gpio.py
ltctplugin/ftflasher/gui.py
ltctplugin/ftflasher/res/spi_flash_chips.json
ltctplugin/ftflasher/res/spi_flash_chips_1hdp.json
ltctplugin/ftflasher/res/spi_flash_chips_2bdk.json
ltctplugin/ftflasher/types.py
ltctplugin/ftflasher/work/bk72xx_boot.py
ltctplugin/ftflasher/work/spi_flash.py
ltctplugin/ftflasher/work/spi_flash_device.py
ltchiptool_ft232_flasher-1.1.0.dist-info/METADATA
ltchiptool_ft232_flasher-1.1.0.dist-info/WHEEL
ltchiptool_ft232_flasher-1.1.0.dist-info/RECORD
